merino/__init__.py
merino/__main__.py
merino/config.py
merino/copy_saved_models.py
merino/pipeline.py
merino/tpipeline.py
merino/iterators/__init__.py
merino/iterators/lemmatizer_iterators.py
merino/iterators/mwt_iterators.py
merino/iterators/ner_iterators.py
merino/iterators/tagger_iterators.py
merino/iterators/tokenizer_iterators.py
merino/models/__init__.py
merino/models/base_models.py
merino/models/classifiers.py
merino/models/crf_model.py
merino/models/lemma_model.py
merino/models/mwt_model.py
merino/models/seq2seq_model.py
merino/utils/__init__.py
merino/utils/base_utils.py
merino/utils/chuliu_edmonds.py
merino/utils/conll.py
merino/utils/conll18_ud_eval.py
merino/utils/mwt_utils.py
merino/utils/ner_utils.py
merino/utils/seq2seq_utils.py
merino/utils/seq2seq_vocabs.py
merino/utils/tagger_utils.py
merino/utils/tbinfo.py
merino/utils/tokenizer_utils.py
uo_parser_beta-0.1.8.dist-info/LICENSE
uo_parser_beta-0.1.8.dist-info/METADATA
uo_parser_beta-0.1.8.dist-info/WHEEL
uo_parser_beta-0.1.8.dist-info/top_level.txt
uo_parser_beta-0.1.8.dist-info/RECORD
